{
  "id": "absorb",
  "name": "Absorb",
  "description": "Universal knowledge ingestion — absorb files, folders, PDFs, emails, LINE chats, Facebook posts, images, web pages, and more into The Vault (Oracle L3) or Memory (L1+L2). Triggers on /absorb, 'scan this repo', 'import this project', 'absorb my files', or 'learn from this'.",
  "context": "fork",
  "version": "1.0.0",
  "category": "intelligence",
  "tags": ["knowledge", "learning", "import", "migration", "absorb", "vault", "ingestion", "parser"],
  "kind": "prompt-pattern",
  "icon": "🧽",
  "alwaysOn": true,
  "defaultEnabled": true,
  "permissions": { "allow": [] },
  "onboarding": {
    "tier": "required",
    "phase": "skills_required",
    "order": 30,
    "title": "Absorb — Knowledge Ingestion",
    "summary": "Ingest files, PDFs, emails, chats, and more into your knowledge base. Optionally connect Oracle Vault for deep storage.",
    "why_it_matters": "This is how your AI learns from your existing documents and data. Oracle Vault is optional but gives you cross-machine search.",
    "estimated_minutes": 2,
    "depends_on": ["memory-server"],
    "facts_schema": {
      "skill_present": "boolean",
      "oracle_configured": "boolean"
    },
    "steps": [
      {"id": "verify", "label": "Verify absorb skill", "kind": "probe", "required": true, "probe": "absorb", "success_sets": ["skill_present"]},
      {"id": "oracle_setup", "label": "Configure Oracle Vault (optional)", "kind": "config", "required": false, "fields": [{"name": "wallet_dir", "type": "path", "required": true}, {"name": "dsn", "type": "string", "required": true}], "success_sets": ["oracle_configured"]}
    ]
  },

  "credentials": [],
  "configSchema": {
    "type": "object",
    "properties": {
      "dry_run": { "type": "boolean", "description": "Preview what would be absorbed without writing anything" },
      "depth": { "type": "string", "enum": ["shallow", "normal", "deep"], "description": "How deeply to analyze sources: shallow=README only, normal=key files, deep=full codebase" },
      "auto_create_todos": { "type": "boolean", "description": "Automatically create TODO items from discovered tasks" },
      "prefer_vault": { "type": "boolean", "description": "Prefer Oracle Vault (L3) when available, otherwise fall back to Memory (L1+L2)" },
      "parser": { "type": "string", "description": "Force a specific parser: text, pdf, email, line, facebook, image, meeting, web, voice_memo, debate" }
    }
  },
  "configDefaults": {
    "dry_run": false,
    "depth": "normal",
    "auto_create_todos": true,
    "prefer_vault": true,
    "parser": null
  },
  "healthCheck": { "type": "none", "intervalSeconds": 0 },
  "dependencies": {
    "skills": ["memory-server"],
    "system": ["python3"],
    "python": ["oracledb"]
  }
}
